<annotation>
	<folder>my-project-name</folder>
	<filename>063_aug_3.jpg</filename>
	<path>/my-project-name/063_aug_3.jpg</path>
	<source>
		<database>Unspecified</database>
	</source>
	<size>
		<width>224</width>
		<height>224</height>
		<depth>3</depth>
	</size>
	<object>
		<name>Utility</name>
		<pose>Unspecified</pose>
		<truncated>0</truncated>
		<difficult>0</difficult>
		<bndbox>
			<xmin>143</xmin>
			<ymin>63</ymin>
			<xmax>224</xmax>
			<ymax>132</ymax>
		</bndbox>
	</object>
	<object>
		<name>Utility</name>
		<pose>Unspecified</pose>
		<truncated>0</truncated>
		<difficult>0</difficult>
		<bndbox>
			<xmin>81</xmin>
			<ymin>28</ymin>
			<xmax>143</xmax>
			<ymax>68</ymax>
		</bndbox>
	</object>
</annotation>