<annotation>
	<folder>my-project-name</folder>
	<filename>309_aug_3.jpg</filename>
	<path>/my-project-name/309_aug_3.jpg</path>
	<source>
		<database>Unspecified</database>
	</source>
	<size>
		<width>224</width>
		<height>224</height>
		<depth>3</depth>
	</size>
	<object>
		<name>Utility</name>
		<pose>Unspecified</pose>
		<truncated>0</truncated>
		<difficult>0</difficult>
		<bndbox>
			<xmin>43</xmin>
			<ymin>56</ymin>
			<xmax>74</xmax>
			<ymax>101</ymax>
		</bndbox>
	</object>
	<object>
		<name>Utility</name>
		<pose>Unspecified</pose>
		<truncated>0</truncated>
		<difficult>0</difficult>
		<bndbox>
			<xmin>130</xmin>
			<ymin>86</ymin>
			<xmax>190</xmax>
			<ymax>146</ymax>
		</bndbox>
	</object>
	<object>
		<name>Utility</name>
		<pose>Unspecified</pose>
		<truncated>0</truncated>
		<difficult>0</difficult>
		<bndbox>
			<xmin>207</xmin>
			<ymin>65</ymin>
			<xmax>224</xmax>
			<ymax>121</ymax>
		</bndbox>
	</object>
	<object>
		<name>Utility</name>
		<pose>Unspecified</pose>
		<truncated>0</truncated>
		<difficult>0</difficult>
		<bndbox>
			<xmin>200</xmin>
			<ymin>133</ymin>
			<xmax>224</xmax>
			<ymax>181</ymax>
		</bndbox>
	</object>
</annotation>